<?xml version="1.0" encoding="UTF-8" standalone="no"?>
<pk><wd nm="attendee&apos;" rd="5,0:304|17,0:2365"/><wd nm="attribut" rd="89,0:3710"/><wd nm="audio" rd="36,0:1498|94,0:2000"/><wd nm="authentication" rd="126,0:1784"/><wd nm="auto" rd="22,0:602|28,0:296|74,0:1690|115,0:117,463|116,0:3279|120,0:887"/><wd nm="auto-complet" rd="43,64:2582"/><wd nm="autocomplet" rd="27,128:29,70,92,773|43,4:47,781,993,2193,2243"/><wd nm="automat" rd="67,0:608"/><wd nm="automatic" rd="17,0:1773|43,1:18|74,0:2038|76,0:93|123,128:10,89,990"/><wd nm="automatical" rd="5,0:273|12,0:166,704,1694,1819,1864,2076|21,0:216|22,0:242|34,0:595,765|35,0:803,1410|38,0:1222|39,0:699|40,32:206,356,418,492|52,0:860|53,0:179,2154|54,64:120,246,449,599,3693|58,0:786|62,0:694|63,0:653|67,0:1452,1624,1783|73,0:131,221,437|74,0:1718|82,0:413,520|83,0:1330,1372|94,0:470|112,0:174,394|114,64:15,1542|115,0:163|116,0:883,2009,4087,4157,5225,6136|119,0:1102|122,0:1344|129,0:1139|130,0:417"/><wd nm="availability" rd="4,0:1096,1747|13,0:1084,1735|14,0:301|17,128:26,84,297,689,1460,2375,2489,3505"/><wd nm="availabl" rd="0,0:1420|1,0:1131|4,0:695,724,956|7,0:230|8,0:229|13,0:683,712,944|14,0:42|17,0:428,761,858,934,1046,1096,1161,2401|20,0:1635|22,0:561|26,1:32,265|28,0:128|36,0:752|39,0:90|43,0:327,2257|46,0:77|47,0:62|48,0:64|51,0:496|58,2:1047,1629,1955,2108,2201|74,0:427,2125,2364|82,0:67|111,0:57|112,0:54|115,0:39|116,0:603,3125|118,0:993,1424|121,0:241|123,0:125|127,0:430,646|131,0:102|132,0:108|133,0:121|134,0:558|135,0:230"/><wd nm="avid" rd="43,0:645"/><wd nm="awar" rd="39,0:626|119,0:572"/><wd nm="away" rd="17,0:2805|115,1:23,655|116,0:3359"/><wd nm="a signature" rd="35,0:1088"/><wd nm="back" rd="19,0:304,443,645|20,0:1338|21,0:514|22,64:329,787,941|39,0:187|46,0:647|59,128:0,2584,2736,3845|65,0:972,1422,1845|69,0:555|77,0:421|106,0:352|116,0:6737,6793|118,0:328,499,512,1262,1842|119,128:0,81,266,1444,1935|121,0:81|123,0:484|129,0:490,873"/><wd nm="background" rd="45,0:152|49,0:439,633|51,0:278|116,0:509"/><wd nm="backslash" rd="55,0:995"/><wd nm="backup" rd="59,64:273,809,3498|119,32:108,157,205,295,331,356,389,501,513,719,742,832,956,999,1032,1054,1091,1118,1178,1193,1285,1308,1372,1395,1500,1565,1615,1673|120,0:1008,1444|121,128:25,61,164,209,223,275,351,631"/><wd nm="bad" rd="42,0:522,784"/><wd nm="ball" rd="118,0:1760"/><wd nm="balloon" rd="74,0:2183"/><wd nm="bana" rd="88,0:490"/><wd nm="banana" rd="52,0:1802,1822,1834,1855,1983,2007,2191,2208,2217,2245|55,0:226,278,285,322,551,601,612,625|88,0:321,353,363,505,514,534,679,700,713,721,730|89,0:3220|94,0:1460,1479"/><wd nm="bananafloat" rd="55,0:267"/><wd nm="bananasboat" rd="55,0:590"/><wd nm="bandanna" rd="55,0:367,409,424,443"/><wd nm="banner" rd="1,0:695"/><wd nm="bar" rd="4,0:1127,3321|13,0:1115,2180|14,0:332|56,0:692|74,0:242,859|86,0:949|89,0:279,2534|91,0:152,241|102,0:1187|103,0:1828"/><wd nm="bas" rd="58,0:643|89,0:5515"/><wd nm="basi" rd="66,0:241|121,0:111"/><wd nm="basic" rd="86,0:221,275|87,0:386|89,0:1886|92,0:655,1550|93,0:183,691|116,0:361"/><wd nm="basic_search" rd="86,0:1185"/><wd nm="bcc" rd="20,0:1506|36,0:766,787|37,0:692|43,0:110|44,32:10,33,66,264,385,443,460,700|90,0:169"/><wd nm="bcc:" rd="44,128:820"/><wd nm="be" rd="0,0:104,900,1134,1498,2194|1,0:572,941,1494|3,0:179|4,0:1193,3162|5,0:128|7,0:412|9,0:428|10,0:412|12,0:511,831,1478|13,0:1181,2021|16,0:760|17,0:1376,2314,2350,2456,2821|20,0:580,686,744|21,0:1146|22,0:43,103,420|23,0:235,263,597|24,0:259|31,0:427,657,707,755,951,985,1245,1313,1353|32,0:139,394|33,0:352,440,1605|34,0:280,670,1146,1720|35,0:548,604|37,0:231,482|38,0:427,606|39,0:497|40,0:72|42,0:73|43,0:468,1492,1593,1862,1944|46,0:367|47,0:371|48,0:104|49,0:266|51,0:784,1085,1250|52,0:655,3192|53,0:767,821,1078,1663,1755,2145|54,0:1379,2190|55,0:36,665|58,0:479,579,1365,1664,1730,2006|59,0:339,682,868,1441,1918,2311,2426|61,0:375,519|64,0:145|65,0:323,450|67,0:497,718,745,754,1102,1251,1450|68,0:55|72,0:97|73,0:450,510|74,0:1194,1512,1585,2080|75,0:270|77,0:371|78,0:342,413,923,1812|79,0:567,600|81,0:937|82,0:411|83,0:217,1584|84,0:136|86,0:692,846|89,0:236,414,1378,2278,2433,2926,3293,3601,4763,5155|90,0:366|92,0:71,737|94,0:1627,1883|95,0:121|96,0:198,1934|98,0:1009|100,0:141|101,0:294,910|102,0:394,766|104,0:310,419|111,0:119,198|113,0:157,756|114,0:790,882|115,0:509|116,0:805,1665,3774,6001,6102,6273|118,0:447|119,0:570,592,844,1169|120,0:1504|125,0:244,316,347,685|126,0:745,1948,2306|127,0:532,1059,1600|128,0:1370|129,0:635|130,0:382|132,0:250,474|134,0:556" sp="1"/><wd nm="becaus" rd="30,0:2033|31,0:95,1792,1878|86,0:400,635|89,0:1982,2221|122,0:1539" sp="1"/><wd nm="becom" rd="38,0:765|43,0:297"/><wd nm="become" rd="1,0:1955|15,0:598"/><wd nm="been" rd="4,0:1432|12,0:1594|13,0:1420|17,0:622|30,0:1677,1724|33,0:1444|34,0:1236,1496,1950|46,0:143|59,0:2756|74,0:1425|78,0:1667|89,0:5383|94,0:173|96,0:703|100,0:123|102,0:574|116,0:1620" sp="1"/><wd nm="beep" rd="76,0:395|113,0:301,1073|116,0:2751"/><wd nm="befor" rd="1,0:144|12,0:762|17,0:1223|21,0:677|33,0:1785|46,0:535|52,0:476,1237|55,0:1015,1104|59,0:2899|62,0:210|67,0:660|74,0:2227|82,0:280|83,0:999|87,0:493|89,0:4785,4901,4941|90,0:521|92,0:1336|103,0:1300|113,0:722,820|116,0:6330|119,0:1039|122,0:371|125,0:622|126,0:427|127,0:134,741|128,0:126,298|129,0:644"/><wd nm="begin" rd="31,0:1134|43,0:914|49,0:780|71,0:716|118,0:165|126,0:436|127,0:750,2073|128,0:307"/><wd nm="behalf" rd="131,0:444,573|132,0:1242,1377|133,0:607,739,929,1058"/><wd nm="behave" rd="43,0:2337"/><wd nm="behavior" rd="43,0:1469|116,0:256,2155|130,128:14,106,1040"/><wd nm="being" rd="27,0:346|28,0:341,573|52,0:2887|54,0:1493,1506|58,0:1080|59,0:2186|116,0:6304|119,0:1439|121,0:493|122,0:351|124,0:1062|126,0:2744|127,0:2184|128,0:1780|131,0:1374"/><wd nm="below" rd="17,0:1026|21,0:996|35,0:763|43,0:1076|74,0:167,698,785,1523|114,0:1004|118,0:109|124,0:454"/><wd nm="beneath" rd="92,0:440"/><wd nm="beside" rd="58,0:1073|124,0:1055"/><wd nm="better" rd="93,0:762"/><wd nm="between" rd="36,0:521|56,0:338|61,0:685|69,128:18,51,798,930|71,0:388|73,0:240|81,0:622|86,0:315|87,0:536|92,0:1686|96,0:770,2456|103,0:296|116,0:6521|122,0:1434|123,0:554" sp="1"/><wd nm="bigger" rd="89,0:5170"/><wd nm="billybob" rd="43,0:974"/><wd nm="birthday" rd="20,0:850,911"/><wd nm="black" rd="116,0:3899"/><wd nm="blank" rd="17,0:2054|36,0:238,331|50,0:325"/><wd nm="bldg3" rd="17,0:2224,2256,2296"/><wd nm="blind" rd="44,0:90"/><wd nm="block" rd="34,0:189,1332,1512,1587"/><wd nm="blu" rd="2,0:284|102,0:633"/><wd nm="boat" rd="55,0:557,608,619,631"/><wd nm="bob" rd="43,0:942,957"/><wd nm="body" rd="1,0:2049|35,0:735|37,0:164,584|38,4:1013,1020,1192|52,0:1264,1281,1353|54,0:1096|80,0:367,582,686|83,0:497,1288|87,0:451|90,0:184|92,0:1710|94,0:1773|116,0:4234,4338,4777,4798"/><wd nm="bold" rd="30,0:528,959,1685|76,0:739|77,0:125|130,0:734"/><wd nm="book" rd="0,0:1036|20,0:1108,1230,1846|21,0:354,656,707,1268|22,0:81,273,346,538|23,32:85,409,569,700,819,852,988|24,128:16,37,131,512|25,0:89,265,284|26,1:27,108,183,207,566|28,64:68,665,698,737,776,1195|29,1:45,77,172,233|33,0:155,1142,1166,1221|35,0:204|43,0:2235|58,0:1484,1948|59,0:1472|78,0:1721|90,32:349,960|96,0:69,1398,1575|116,0:192,5315,5393,5448|120,4:782|122,0:485|127,0:423|133,0:1705,1805|134,0:537"/><wd nm="book," rd="21,64:1443"/><wd nm="books," rd="28,64:946"/><wd nm="border" rd="49,0:449,577"/><wd nm="bos" rd="54,0:441"/><wd nm="both" rd="6,0:968|52,0:352|55,0:857|69,0:351|86,0:149,607|88,0:338|89,0:1809,2191|92,0:859"/><wd nm="bottom" rd="0,0:2039|30,0:228|65,0:593,690,1537,1960|72,0:459|81,0:304,419|102,0:924,1042"/><wd nm="bounc" rd="42,0:453,870"/><wd nm="bounce" rd="42,0:51,509,760"/><wd nm="box" rd="4,0:3137,3214|13,0:1996,2073|20,0:1042|21,0:993,1126|23,0:136|33,0:1763|35,0:760|43,0:2171|53,0:1521,1533,1579|54,0:3384|56,0:962|60,0:401|69,0:245|85,32:105,251,284|86,0:805,965|89,0:2392,2588|90,0:238,652,1073,1249|92,0:482,1020|94,0:383,539|103,0:1647|114,0:618|115,0:489|116,0:1083,3075|121,0:302|135,0:288"/><wd nm="boxe" rd="43,0:113|59,0:1610|86,0:500|87,0:668|89,0:2082,2327|92,0:428"/><wd nm="boxman" rd="86,0:1145"/><wd nm="br" rd="44,0:504"/><wd nm="breakfast" rd="88,0:373"/><wd nm="brief" rd="30,0:1837"/><wd nm="briefcas" rd="0,128:9,83,92,150,197,206,465,501,551,627,672,725,742,766,784,832,873,946,1104,1144,1166,1225,1264,1286,1514,1540,1599,1921,1993,2166,2175,2316,2630|33,64:120,678,876,894,920,2062|49,1:48|50,64:55,200,277,678,1009|51,0:89,1313|58,0:1209,1510|59,0:164|65,2:1609,1684,1709|96,0:89,1420,1595|120,4:1181,1333|122,0:592|125,0:476|132,0:329|133,16:2616,2714,2781"/><wd nm="briefcase," rd="33,64:1913"/><wd nm="briefcasetoolbar" rd="51,0:412"/><wd nm="brink" rd="43,0:436,649,656,2089,2128"/><wd nm="brows" rd="0,0:1619,1743|8,0:445|28,0:245|33,0:744|35,0:910|51,0:1229|59,0:2100,2405|78,0:763"/><wd nm="browser" rd="34,0:694,758,1811,1918,2248,2381,2477,2668|50,0:584|56,0:763|58,0:1554|60,0:108|76,0:607,651|113,0:1164,1210|116,0:2941,2985,6388|134,0:236|135,0:339"/><wd nm="browser&apos;" rd="74,0:2518|79,0:510|89,0:4628"/><wd nm="browserplu" rd="113,0:624"/><wd nm="budget" rd="92,0:261"/><wd nm="build" rd="4,0:1571|13,0:1559|17,0:2208|86,0:243|87,128:0,1422"/><wd nm="builder" rd="89,0:1850"/><wd nm="built" rd="63,0:638"/><wd nm="bullet" rd="45,0:138"/><wd nm="busines" rd="25,0:105,163|58,0:1876|116,0:5139"/><wd nm="busy" rd="4,0:935,1029,1825|13,0:923,1017,1813|14,1:29,204,359|17,0:171|120,0:1167"/><wd nm="but" rd="4,0:1207|6,0:553|9,0:296|12,0:1067|13,0:1195|17,0:817|19,0:405|20,0:1159|31,0:1450|42,0:537|43,0:966|44,0:169|51,0:794|52,0:255,305,342,610,2237,3203|55,0:310,432|64,0:328|67,0:480,728|72,0:348|73,0:331|82,0:202|83,0:1660|88,0:524|91,0:374|92,0:332|94,0:1346,1987|96,4:658,720|111,0:252|115,0:569|116,0:1524|118,0:1110|119,0:567|122,0:1067|129,0:336|131,0:314,763|132,0:1110,1573|133,0:478" sp="1"/><wd nm="button" rd="20,0:108|38,0:812|44,0:463|54,0:2772|56,0:135,189,893|71,0:169|85,0:712|92,0:455|107,0:213"/><wd nm="by" rd="4,0:846|8,0:717|9,0:318,663|12,0:1314,2252|13,0:834|15,0:119|17,0:701|20,0:70,116,1140,1172,1185,1801|21,0:1157|22,0:721|23,0:199,722|30,0:340,356,771,1608,2217,2257,2401|31,0:86,366|34,0:196,355,398,506,2257|38,0:870,1152,1262|43,0:1111,1603|50,0:724|52,0:2360|55,0:866|56,0:781|61,0:88|63,0:620|65,0:115|66,0:165|67,0:199,358,647,898,1347,1707,1866|69,0:496|70,0:60|72,0:105,121,176|74,0:870|76,0:392,715|77,0:441|78,0:1270|80,0:22|81,0:128,588|82,0:338|84,0:275|87,0:247,915|89,0:242,420,487,503,1080,1424,1583,1611|90,0:404,503|91,0:127,157,365|92,0:85,1166,1424|93,0:89,778|94,0:114,129,985,1391,1509|96,4:852,884,1249|102,0:183,213,1223,1341|103,0:30,883|106,0:289|108,0:70,104|113,0:298,1070|116,0:946,2748,4440,4606,5606,5961|118,0:255|120,0:351|126,0:2346|127,0:1641|128,0:1410|129,0:799" sp="1"/></pk>